LICENSE
README.md
setup.py
sickserv/__init__.py
sickserv/client.py
sickserv/rc4.py
sickserv/server.py
sickserv/server_ws.py
sickserv/util.py
sickserv.egg-info/PKG-INFO
sickserv.egg-info/SOURCES.txt
sickserv.egg-info/dependency_links.txt
sickserv.egg-info/requires.txt
sickserv.egg-info/top_level.txt