Metadata-Version: 2.1
Name: sickserv
Version: 0.1.3
Summary: sickserv
Home-page: https://github.com/vesche/sickserv
Author: Austin Jackson
Author-email: vesche@protonmail.com
License: MIT
Platform: UNKNOWN
Classifier: Development Status :: 4 - Beta
Classifier: Intended Audience :: Information Technology
Classifier: License :: OSI Approved :: MIT License
Classifier: Programming Language :: Python :: 3
Classifier: Programming Language :: Python :: 3.9
Classifier: Topic :: Internet
Classifier: Topic :: Security
Requires-Python: >=3
License-File: LICENSE
